{
  "$schema": "https://biomejs.dev/schemas/1.9.4/schema.json",
  "vcs": {
    "enabled": true,
    "clientKind": "git",
    "useIgnoreFile": true
  },
  "files": {
    "maxSize": 10000000,
    "ignore": [
      "**/*.eslintrc.js",
      "**/*.json",
      "**/node_modules",
      "**/dist",
      "**/.idea",
      "**/coverage",
      "**/pnpm-lock.yaml"
    ]
  },
  "formatter": {
    "enabled": true,
    "useEditorconfig": true,
    "formatWithErrors": false,
    "indentStyle": "space",
    "indentWidth": 2,
    "lineEnding": "lf",
    "lineWidth": 120,
    "attributePosition": "auto",
    "bracketSpacing": true,
    "ignore": ["**/node_modules/*", "**/dist/*", "**/.idea", "**/coverage", "**/pnpm-lock.yaml", "**/test/*", "*.spec.ts"]
  },
  "linter": {
    "rules": {
      "recommended": true,
      "style": {
        "useImportType": "off",
        "useNodejsImportProtocol": "off",
        "noNonNullAssertion": "error"
      },
      "correctness": {
        "noUnusedVariables": {
          "level": "error",
          "fix": "safe"
        },
        "noUnusedFunctionParameters": "off",
        "noUnusedImports": "error",
        "noUndeclaredDependencies": "off"
      },
      "performance": {
        "noDelete": {
          "level": "error"
        }
      },
      "complexity": {
        "useLiteralKeys": "warn",
        "noForEach": "warn"
      }
    },
    "ignore": [
      "**/*.eslintrc.js",
      "**/*.json",
      "**/node_modules",
      "**/dist",
      "**/.idea",
      "**/coverage",
      "**/pnpm-lock.yaml",
      "**/test/*",
      "*.spec.ts"
    ]
  },
  "javascript": {
    "formatter": {
      "semicolons": "asNeeded",
      "quoteStyle": "single",
      "trailingCommas": "es5",
      "lineWidth": 120,
      "indentStyle": "space"
    },
    "parser": {
      "unsafeParameterDecoratorsEnabled": true
    }
  },
  "json": {
    "parser": {
      "allowComments": true
    },
    "formatter": {
      "enabled": false
    }
  },
  "organizeImports": {
    "enabled": true
  },
  "overrides": [
    {
      "include": ["*.ts", "*.tsx", "*.mts", "*.cts"],
      "ignore": [
        "**/*.eslintrc.js",
        "**/*.json",
        "**/node_modules",
        "**/dist",
        "**/.idea",
        "**/coverage",
        "**/pnpm-lock.yaml"
      ],
      "linter": {
        "rules": {
          "correctness": {
            "noConstAssign": "off",
            "noGlobalObjectCalls": "off",
            "noInvalidConstructorSuper": "off",
            "noNewSymbol": "off",
            "noSetterReturn": "off",
            "noUndeclaredVariables": "off",
            "noUnreachable": "off",
            "noUnreachableSuper": "off"
          },
          "style": {
            "noArguments": "error",
            "noVar": "error",
            "useConst": "error"
          },
          "suspicious": {
            "noDuplicateClassMembers": "off",
            "noDuplicateObjectKeys": "off",
            "noDuplicateParameters": "off",
            "noFunctionAssign": "off",
            "noImportAssign": "off",
            "noRedeclare": "off",
            "noUnsafeNegation": "off",
            "useGetterReturn": "off"
          }
        }
      }
    }
  ]
}
